ojbk/__init__.py
ojbk/auth.py
ojbk/logtracker.py
ojbk/base/__init__.py
ojbk/base/rabbitmq.py
ojbk-0.0.6.dist-info/METADATA
ojbk-0.0.6.dist-info/WHEEL
ojbk-0.0.6.dist-info/entry_points.txt
ojbk-0.0.6.dist-info/top_level.txt
ojbk-0.0.6.dist-info/RECORD
