Metadata-Version: 2.1
Name: ojbk
Version: 0.0.6
Summary: ok
Home-page: https://github.com/private_repo/uuidentifier
Author: slipper
Author-email: r2fscg@gmail.com
License: UNKNOWN
Platform: UNKNOWN
Classifier: Programming Language :: Python :: 3
Classifier: License :: OSI Approved :: MIT License
Classifier: Operating System :: OS Independent
Requires-Dist: codefast
Requires-Dist: fire
Requires-Dist: pika
Requires-Dist: simauth
